data_gentry/__init__.py
data_gentry/__main__.py
data_gentry/chunking.py
data_gentry/connection.py
data_gentry/db_models.py
data_gentry/embeddings.py
data_gentry/load.py
data_gentry/preprocessors.py
data_gentry/retrieval/__init__.py
data_gentry/retrieval/fuse.py
data_gentry/retrieval/join.py
data_gentry/retrieval/pipeline.py
data_gentry/retrieval/score.py
data_gentry/settings.py
data_gentry/utils.py
data_gentry-0.1.2.dist-info/WHEEL
data_gentry-0.1.2.dist-info/METADATA
data_gentry-0.1.2.dist-info/RECORD
