Metadata-Version: 2.3
Name: data-gentry
Version: 0.1.2
Summary: A library for packaging together data + documentation into an agent-friendly duckdb artifact.
Requires-Dist: boto3>=1.42.5
Requires-Dist: duckdb>=1.4.3
Requires-Dist: duckdb-engine>=0.17.0
Requires-Dist: pymupdf4llm>=0.2.7
Requires-Dist: pytz>=2025.2
Requires-Dist: semchunk>=3.2.5
Requires-Dist: sqlalchemy>=2.0.45
Requires-Dist: strands-agents>=1.19.0
Requires-Dist: types-boto3[bedrock,bedrock-runtime]>=1.42.9
Requires-Python: >=3.14
